jupyter_server_ydoc_codio/__init__.py
jupyter_server_ydoc_codio/_version.py
jupyter_server_ydoc_codio/app.py
jupyter_server_ydoc_codio/custom_stores.py
jupyter_server_ydoc_codio/handlers.py
jupyter_server_ydoc_codio/loaders.py
jupyter_server_ydoc_codio/pytest_plugin.py
jupyter_server_ydoc_codio/rooms.py
jupyter_server_ydoc_codio/stores.py
jupyter_server_ydoc_codio/test_utils.py
jupyter_server_ydoc_codio/utils.py
jupyter_server_ydoc_codio/websocketserver.py
jupyter_server_ydoc_codio/events/awareness.yaml
jupyter_server_ydoc_codio/events/fork.yaml
jupyter_server_ydoc_codio/events/session.yaml
jupyter_server_ydoc_codio-2.1.1.data/data/etc/jupyter/jupyter_server_config.d/jupyter_collaboration.json
jupyter_server_ydoc_codio-2.1.1.dist-info/METADATA
jupyter_server_ydoc_codio-2.1.1.dist-info/WHEEL
jupyter_server_ydoc_codio-2.1.1.dist-info/licenses/LICENSE
jupyter_server_ydoc_codio-2.1.1.dist-info/RECORD
