Metadata-Version: 2.4
Name: jupyter-server-ydoc-codio
Version: 2.1.1
Summary: fork of jupyter-server extension integrating collaborative shared models.
Project-URL: Documentation, https://jupyterlab-realtime-collaboration.readthedocs.io/
Project-URL: Repository, https://github.com/codio/jupyter-collaboration
Project-URL: Changelog, https://jupyterlab-realtime-collaboration.readthedocs.io/en/latest/changelog.html
Project-URL: Source, https://github.com/codio/jupyter-collaboration/tree/main/projects/jupyter-server-ydoc-codio
Project-URL: Issues, https://github.com/codio/jupyter-collaboration/issues/new/choose
Author-email: Jupyter Development Team <jupyter@googlegroups.com>
License: # Licensing terms
License-File: LICENSE
Classifier: Framework :: Jupyter
Classifier: Intended Audience :: Developers
Classifier: Intended Audience :: Science/Research
Classifier: Intended Audience :: System Administrators
Classifier: License :: OSI Approved :: BSD License
Classifier: Programming Language :: Python
Classifier: Programming Language :: Python :: 3.8
Classifier: Programming Language :: Python :: 3.9
Classifier: Programming Language :: Python :: 3.10
Classifier: Programming Language :: Python :: 3.11
Classifier: Programming Language :: Python :: 3.12
Requires-Python: >=3.8
Requires-Dist: jsonschema>=4.18.0
Requires-Dist: jupyter-events>=0.11.0
Requires-Dist: jupyter-server-fileid<1,>=0.7.0
Requires-Dist: jupyter-server<3.0.0,>=2.15.0
Requires-Dist: jupyter-ydoc<4.0.0,>=3.0.3
Requires-Dist: pycrdt
Requires-Dist: pycrdt-websocket<0.17.0,>=0.16.0
Provides-Extra: test
Requires-Dist: anyio; extra == 'test'
Requires-Dist: coverage; extra == 'test'
Requires-Dist: dirty-equals; extra == 'test'
Requires-Dist: httpx-ws>=0.5.2; extra == 'test'
Requires-Dist: importlib-metadata>=4.8.3; (python_version < '3.10') and extra == 'test'
Requires-Dist: jupyter-server-fileid[test]; extra == 'test'
Requires-Dist: jupyter-server[test]>=2.15.0; extra == 'test'
Requires-Dist: pytest-cov; extra == 'test'
Requires-Dist: pytest>=7.0; extra == 'test'
